sftp_downloader/__init__.py
sftp_downloader/cli.py
sftp_downloader/downloader.py
sftp_downloader/downloader_ver1.py
sftp_downloader/logger.py
sftp_downloader-0.1.0.dist-info/licenses/LICENSE
sftp_downloader-0.1.0.dist-info/METADATA
sftp_downloader-0.1.0.dist-info/WHEEL
sftp_downloader-0.1.0.dist-info/entry_points.txt
sftp_downloader-0.1.0.dist-info/top_level.txt
sftp_downloader-0.1.0.dist-info/RECORD
