Metadata-Version: 2.4
Name: sftp-downloader
Version: 0.1.0
Summary: SFTP sunucusundan klasörleri alt dizinlerle birlikte indirmek için araç
Author-email: Ad Soyad <email@domain.com>
Requires-Python: >=3.8
License-File: LICENSE
Requires-Dist: paramiko>=3.0
Requires-Dist: tqdm>=4.0
Dynamic: license-file
